[{"Prop_ID":"X172","Name":"Allerton Playground","Location":"Bouck & Throop avenues","Accessible":"N","lat":"40.866","lon":"-73.8505"},{"Prop_ID":"X002","Name":"Bronx Park East","Location":"Bronx Park East & Birchall Avenue","Accessible":"N","lat":"40.8512","lon":"-73.87"},{"Prop_ID":"X102","Name":"Ciccarone","Location":"Arthur Avenue & East 188th Street","Accessible":"N","lat":"40.856","lon":"-73.887"},{"Prop_ID":"X122","Name":"Colucci","Location":"Mayflower & Wilkerson avenues","Accessible":"N","lat":"40.8534","lon":"-73.8345"},{"Prop_ID":"X092","Name":"Indian Field Van Cortlandt","Location":"West 233rd Street & Van Cortlandt Park East","Accessible":"N","lat":"40.8968","lon":"-73.8772"},{"Prop_ID":"X163","Name":"Loreto","Location":"Morris Park & Tomlinson Avenue","Accessible":"N","lat":"40.8486","lon":"-73.8516"},{"Prop_ID":"X039","Name":"Pelham Bay","Location":"New England Expressway & Middletown Road","Accessible":"N","lat":"40.848","lon":"-73.8252"},{"Prop_ID":"X104","Name":"Williamsbridge Oval","Location":"West 208th Street & Bainbridge Avenue","Accessible":"N","lat":"40.8776","lon":"-73.8774"},{"Prop_ID":"B349","Name":"Bath Beach Playground","Location":"17th Avenue & Shore Road","Accessible":"N","lat":"40.5946","lon":"-73.9936"},{"Prop_ID":"B019","Name":"Carroll Park","Location":"Carroll, Smith & Court streets","Accessible":"N","lat":"40.6811","lon":"-73.9954"},{"Prop_ID":"B125","Name":"Dreier-Offerman Park","Location":"Bay 44th & Cropsey Avenue","Accessible":"N","lat":"40.5846","lon":"-73.9951"},{"Prop_ID":"B028","Name":"Dyker Park","Location":"86th Street between 13-14 avenues","Accessible":"N","lat":"40.6129","lon":"-74.0124"},{"Prop_ID":"B057","Name":"Marine Park","Location":"Gerritsen, Flatbush & Filmore avenues, Jamaica Bay","Accessible":"N","lat":"40.5968","lon":"-73.9285"},{"Prop_ID":"B058","Name":"McCarren Park","Location":"Union Avenue and Bayard Street","Accessible":"N","lat":"40.7195","lon":"-73.9519"},{"Prop_ID":"M038","Name":"James J. Walker Park","Location":"Clarkson Street & 7th Avenue","Accessible":"N","lat":"40.73","lon":"-74.0063"},{"Prop_ID":"M108A","Name":"Louis Cuvillier Park","Location":"125th Street & FDR Drive","Accessible":"N","lat":"40.8009","lon":"-73.9309"},{"Prop_ID":"Q004","Name":"Astoria Park","Location":"Lower Shore Boulevard, 23rd Avenue & 23rd Road","Accessible":"N","lat":"40.7804","lon":"-73.9197"},{"Prop_ID":"Q006","Name":"Bowne Park","Location":"29th & 32nd avenues & 158th -159th streets","Accessible":"N","lat":"40.7708","lon":"-73.8066"},{"Prop_ID":"Q008","Name":"Brookville Park","Location":"147th Avenue & 235th Street & Brookville Boulevard & South Conduit","Accessible":"N","lat":"40.6639","lon":"-73.741"},{"Prop_ID":"Q021","Name":"Cunningham Park","Location":"Union Turnpike, 196th Place","Accessible":"N","lat":"40.7267","lon":"-73.7755"},{"Prop_ID":"Q385","Name":"Ditmars Park","Location":"Steinway Street between 23rd Avenue & Ditmars Boulevard","Accessible":"N","lat":"40.7716","lon":"-73.9072"},{"Prop_ID":"Q015","Name":"Dry Harbor","Location":"80th Street & Myrtle Avenue","Accessible":"N","lat":"40.7027","lon":"-73.8684"},{"Prop_ID":"Q302","Name":"Evergreen Park","Location":"Felix & Seneca avenues & 75th Avenue","Accessible":"N","lat":"40.6972","lon":"-73.8964"},{"Prop_ID":"Q102","Name":"Juniper North","Location":"77 Place, Juniper Boulevard South","Accessible":"N","lat":"40.7211","lon":"-73.8775"},{"Prop_ID":"Q024","Name":"Kissena Park","Location":"Oak & 162 Street","Accessible":"N","lat":"40.749","lon":"-73.8063"},{"Prop_ID":"Q369","Name":"Louis Pasteur Park","Location":"52nd Avenue between 248th Street & Marathon Parkway","Accessible":"N","lat":"40.7617","lon":"-73.7354"},{"Prop_ID":"Q131","Name":"Maurice Park","Location":"Maurice Avenue & Borden Avenue & 54th Avenue & 63rd Street","Accessible":"N","lat":"40.7276","lon":"-73.9039"},{"Prop_ID":"Q118","Name":"PO Nicholas Demutiis Park","Location":"Liberty Avenue, 101st - 102nd streets","Accessible":"N","lat":"40.6818","lon":"-73.8393"},{"Prop_ID":"Q029","Name":"William F. Moore Park","Location":"108th Street & 51st Avenue","Accessible":"N","lat":"40.7437","lon":"-73.8555"},{"Prop_ID":"R076","Name":"Markham Playground","Location":"Willowbrook Parkway, Forest Avenue & Houston Street","Accessible":"N","lat":"40.6246","lon":"-74.1456"},{"Prop_ID":"R123","Name":"Skyline Playground","Location":"Arnold Street & Prospect Avenue between Harvard Avenue & Clyde Place","Accessible":"N","lat":"40.6398","lon":"-74.09"},{"Prop_ID":"R046","Name":"South Beach","Location":"Father Capodanno Boulevard & Doty Avenue","Accessible":"N","lat":"40.593","lon":"-74.0626"},{"Prop_ID":"Q126","Name":"Francis Lewis Park","Location":"3rd Avenue & Parsons Boulevard (Whitestone)","Accessible":"N","lat":"40.7965","lon":"-73.8252"},{"Prop_ID":"B431","Name":"Brooklyn Bridge Park","Location":"Pier 2","Accessible":"N","lat":"40.6991","lon":"-73.9987"}]